[
  {
    "id": "andhrapradesh",
    "state_id": 1,
    "name": "Andhra Pradesh",
    "dance": "Kuchipudi",
    "festival": "Sankranti",
    "description": "Kuchipudi is one of the eight major Indian classical dances and originated in Andhra Pradesh.",
    "image": "andhra.jpg",
    "svg": "Andhra.svg",
    "wikiLink": "https://en.wikipedia.org/wiki/Andhra_Pradesh",
    "official_website": "https://www.ap.gov.in",
    "isActive": true
  },
  {
    "id": "arunachalpradesh",
    "state_id": 2,
    "name": "Arunachal Pradesh",
    "dance": "Yak Dance",
    "festival": "Losar, Reh",
    "description": "The Yak dance is a traditional dance form performed during major festivals in Arunachal Pradesh.",
    "image": "arunachal.jpeg",
    "svg": "ArunachalPradesh.svg",
    "wikiLink": "https://en.wikipedia.org/wiki/Arunachal_Pradesh",
    "official_website": "https://www.arunachalpradesh.gov.in",
    "isActive": true
  },
  {
    "id": "assam",
    "state_id": 3,
    "name": "Assam",
    "dance": "Bihu Dance",
    "festival": "Bihu",
    "description": "The Bihu dance is an energetic and vibrant folk dance performed during the Bihu festival in Assam.",
    "image": "assam.jpg",
    "svg": "assam.svg",
    "wikiLink": "https://en.wikipedia.org/wiki/Assam",
    "official_website": "https://www.assam.gov.in",
    "isActive": true
  },
  {
    "id": "bihar",
    "state_id": 4,
    "name": "Bihar",
    "dance": "Jat-Jatin",
    "festival": "Chhath Puja",
    "description": "Jat-Jatin is a popular folk dance of Bihar that represents rural life and relationships.",
    "image": "bihar.jpeg",
    "svg": "Bihar.svg",
    "wikiLink": "https://en.wikipedia.org/wiki/Bihar",
    "official_website": "https://state.bihar.gov.in",
    "isActive": true
  },
  {
    "id": "chhattisgarh",
    "state_id": 5,
    "name": "Chhattisgarh",
    "dance": "Panthi Dance",
    "festival": "Bastar Dussehra",
    "description": "Panthi Dance is a traditional dance performed by the Satnami community of Chhattisgarh.",
    "image": "chattisgarh.jpg",
    "svg": "Chhatisgarh.svg",
    "wikiLink": "https://en.wikipedia.org/wiki/Chhattisgarh",
    "official_website": "https://www.cgstate.gov.in",
    "isActive": true
  },
  {
    "id": "delhi",
    "state_id": 29,
    "name": "Delhi",
    "dance": "Dilli Kathak",
    "festival": "Republic Day Parade",
    "description": "Delhi is known for its rich cultural heritage and performances of classical and contemporary Kathak dance.",
    "image": "delhi.jpg",
    "svg": "Delhi.svg",
    "wikiLink": "https://en.wikipedia.org/wiki/Delhi",
    "official_website": "https://delhi.gov.in",
    "isActive": true
  },
  {
    "id": "goa",
    "state_id": 6,
    "name": "Goa",
    "dance": "Dekhnni",
    "festival": "Carnival",
    "description": "Dekhnni is a semi-classical Goan dance form that blends Indian and Western influences.",
    "image": "goa.jpg",
    "svg": "Goa.svg",
    "wikiLink": "https://en.wikipedia.org/wiki/Goa",
    "official_website": "https://www.goa.gov.in",
    "isActive": true
  },
  {
    "id": "gujarat",
    "state_id": 7,
    "name": "Gujarat",
    "dance": "Garba",
    "festival": "Navratri",
    "description": "Garba is a popular folk dance of Gujarat performed during the Navratri festival.",
    "image": "Gujrat.jpg",
    "svg": "Gujrat.svg",
    "wikiLink": "https://en.wikipedia.org/wiki/Gujarat",
    "official_website": "https://gujaratindia.gov.in",
    "isActive": true
  },
  {
    "id": "haryana",
    "state_id": 8,
    "name": "Haryana",
    "dance": "Phag Dance",
    "festival": "Teej",
    "description": "Phag Dance is a vibrant folk dance of Haryana performed during the harvest season.",
    "image": "Haryana.jpeg",
    "svg": "Harayana.svg",
    "wikiLink": "https://en.wikipedia.org/wiki/Haryana",
    "official_website": "https://haryana.gov.in",
    "isActive": true
  },
  {
    "id": "himachalpradesh",
    "state_id": 9,
    "name": "Himachal Pradesh",
    "dance": "Nati",
    "festival": "Kullu Dussehra",
    "description": "Nati is a traditional folk dance of Himachal Pradesh, known for its slow rhythm and graceful movements.",
    "image": "himachal.jpg",
    "svg": "HimachalPradesh.svg",
    "wikiLink": "https://en.wikipedia.org/wiki/Himachal_Pradesh",
    "official_website": "https://himachal.nic.in",
    "isActive": true
  },
  {
    "id": "jammuandkashmir",
    "state_id": 30,
    "name": "Jammu and Kashmir",
    "dance": "Rouf",
    "festival": "Hemis Festival",
    "description": "Jammu and Kashmir is renowned for its traditional Rouf dance and vibrant cultural festivals like the Hemis Festival.",
    "image": "kashmir.jpeg",
    "svg": "Kashmir.svg",
    "wikiLink": "https://en.wikipedia.org/wiki/Jammu_and_Kashmir",
    "official_website": "https://jk.gov.in",
    "isActive": true
  },
  {
    "id": "jharkhand",
    "state_id": 10,
    "name": "Jharkhand",
    "dance": "Chhau Dance",
    "festival": "Sarhul",
    "description": "Chhau Dance is a semi-classical dance form that incorporates martial arts and storytelling.",
    "image": "jharkhand.jpg",
    "svg": "Jharkhand.svg",
    "wikiLink": "https://en.wikipedia.org/wiki/Jharkhand",
    "official_website": "https://www.jharkhand.gov.in",
    "isActive": true
  },
  {
    "id": "karnataka",
    "state_id": 11,
    "name": "Karnataka",
    "dance": "Yakshagana",
    "festival": "Dasara",
    "description": "Yakshagana is a traditional theater and dance form that originated in Karnataka.",
    "image": "karnataka.jpg",
    "svg": "Karnataka.svg",
    "wikiLink": "https://en.wikipedia.org/wiki/Karnataka",
    "official_website": "https://www.karnataka.gov.in",
    "isActive": true
  },
  {
    "id": "kerala",
    "state_id": 12,
    "name": "Kerala",
    "dance": "Kathakali",
    "festival": "Onam",
    "description": "Kathakali is a classical dance-drama from Kerala, known for its elaborate costumes and makeup.",
    "image": "kerala.jpg",
    "svg": "Kerala.svg",
    "wikiLink": "https://en.wikipedia.org/wiki/Kerala",
    "official_website": "https://www.kerala.gov.in",
    "isActive": true
  },
  {
    "id": "madhyapradesh",
    "state_id": 13,
    "name": "Madhya Pradesh",
    "dance": "Matki Dance",
    "festival": "Khajuraho Dance Festival",
    "description": "Matki Dance is a traditional folk dance of Madhya Pradesh performed during celebrations.",
    "image": "madhyapradesh.jpg",
    "svg": "MadhyaPradesh.svg",
    "wikiLink": "https://en.wikipedia.org/wiki/Madhya_Pradesh",
    "official_website": "https://www.mp.gov.in",
    "isActive": true
  },
  {
    "id": "maharashtra",
    "state_id": 14,
    "name": "Maharashtra",
    "dance": "Lavani",
    "festival": "Ganesh Chaturthi",
    "description": "Lavani is a traditional folk dance of Maharashtra known for its energetic and graceful performances.",
    "image": "maharashtra.jpg",
    "svg": "Maharashtra.svg",
    "wikiLink": "https://en.wikipedia.org/wiki/Maharashtra",
    "official_website": "https://www.maharashtra.gov.in",
    "isActive": true
  },
  {
    "id": "manipur",
    "state_id": 15,
    "name": "Manipur",
    "dance": "Raas Leela",
    "festival": "Yaoshang",
    "description": "Raas Leela is a classical Manipuri dance depicting the love story of Radha and Krishna.",
    "image": "manipur.jpeg",
    "svg": "Manipur.svg",
    "wikiLink": "https://en.wikipedia.org/wiki/Manipur",
    "official_website": "https://manipur.gov.in",
    "isActive": true
  },
  {
    "id": "meghalaya",
    "state_id": 16,
    "name": "Meghalaya",
    "dance": "Nongkrem Dance",
    "festival": "Shad Suk Mynsiem",
    "description": "The Nongkrem Dance is a traditional tribal dance performed by the Khasi community in Meghalaya.",
    "image": "meghalaya.jpeg",
    "svg": "Meghalaya.svg",
    "wikiLink": "https://en.wikipedia.org/wiki/Meghalaya",
    "official_website": "https://www.meghalaya.gov.in",
    "isActive": true
  },
  {
    "id": "mizoram",
    "state_id": 17,
    "name": "Mizoram",
    "dance": "Cheraw Dance",
    "festival": "Chapchar Kut",
    "description": "Cheraw Dance, also known as Bamboo Dance, is a popular traditional dance of Mizoram.",
    "image": "mizoram.jpg",
    "svg": "Mizoram.svg",
    "wikiLink": "https://en.wikipedia.org/wiki/Mizoram",
    "official_website": "https://mizoram.gov.in",
    "isActive": true
  },
  {
    "id": "nagaland",
    "state_id": 18,
    "name": "Nagaland",
    "dance": "Chang Lo",
    "festival": "Hornbill Festival",
    "description": "Chang Lo is a traditional folk dance of the Chang tribe in Nagaland.",
    "image": "nagaland.jpeg",
    "svg": "Nagaland.svg",
    "wikiLink": "https://en.wikipedia.org/wiki/Nagaland",
    "official_website": "https://www.nagaland.gov.in",
    "isActive": true
  },
  {
    "id": "odisha",
    "state_id": 19,
    "name": "Odisha",
    "dance": "Odissi",
    "festival": "Rath Yatra",
    "description": "Odissi is one of the eight major Indian classical dance forms and originated in Odisha.",
    "image": "odisha.jpg",
    "svg": "Odisha.svg",
    "wikiLink": "https://en.wikipedia.org/wiki/Odisha",
    "official_website": "https://www.odisha.gov.in",
    "isActive": true
  },
  {
    "id": "punjab",
    "state_id": 20,
    "name": "Punjab",
    "dance": "Bhangra",
    "festival": "Lohri",
    "description": "Bhangra is a vibrant and energetic folk dance of Punjab, performed during harvest festivals.",
    "image": "punjab.jpg",
    "svg": "punjab.svg",
    "wikiLink": "https://en.wikipedia.org/wiki/Punjab,_India",
    "official_website": "https://www.punjab.gov.in",
    "isActive": true
  },
  {
    "id": "rajasthan",
    "state_id": 21,
    "name": "Rajasthan",
    "dance": "Ghoomar",
    "festival": "Gangaur",
    "description": "Ghoomar is a traditional folk dance of Rajasthan performed by women in colorful attire.",
    "image": "rajasthan.jpg",
    "svg": "Rajasthan.svg",
    "wikiLink": "https://en.wikipedia.org/wiki/Rajasthan",
    "official_website": "https://www.rajasthan.gov.in",
    "isActive": true
  },
  {
    "id": "sikkim",
    "state_id": 22,
    "name": "Sikkim",
    "dance": "Singhi Chham",
    "festival": "Losar",
    "description": "Singhi Chham is a traditional mask dance of Sikkim performed during the Losar festival.",
    "image": "sikkim.jpg",
    "svg": "Sikkim.svg",
    "wikiLink": "https://en.wikipedia.org/wiki/Sikkim",
    "official_website": "https://www.sikkim.gov.in",
    "isActive": true
  },
  {
    "id": "tamilnadu",
    "state_id": 23,
    "name": "Tamil Nadu",
    "dance": "Bharatanatyam",
    "festival": "Pongal",
    "description": "Bharatanatyam is one of the oldest classical dance forms of India, originating in Tamil Nadu.",
    "image": "tamilnadu.jpg",
    "svg": "TamilNadu.svg",
    "wikiLink": "https://en.wikipedia.org/wiki/Tamil_Nadu",
    "official_website": "https://www.tn.gov.in",
    "isActive": true
  },
  {
    "id": "telangana",
    "state_id": 24,
    "name": "Telangana",
    "dance": "Perini Shivatandavam",
    "festival": "Bonalu",
    "description": "Perini Shivatandavam is an ancient dance form dedicated to Lord Shiva, revived in Telangana.",
    "image": "telangana.jpg",
    "svg": "Telangana.svg",
    "wikiLink": "https://en.wikipedia.org/wiki/Telangana",
    "official_website": "https://www.telangana.gov.in",
    "isActive": true
  },
  {
    "id": "tripura",
    "state_id": 25,
    "name": "Tripura",
    "dance": "Hojagiri",
    "festival": "Kharchi Puja",
    "description": "Hojagiri is a traditional tribal dance performed by the Reang community of Tripura.",
    "image": "tripura.jpg",
    "svg": "Tripura.svg",
    "wikiLink": "https://en.wikipedia.org/wiki/Tripura",
    "official_website": "https://www.tripura.gov.in",
    "isActive": true
  },
  {
    "id": "uttarpradesh",
    "state_id": 26,
    "name": "Uttar Pradesh",
    "dance": "Kathak",
    "festival": "Diwali",
    "description": "Kathak is one of the eight major Indian classical dance forms and is widely practiced in Uttar Pradesh.",
    "image": "uttarpradesh.jpg",
    "svg": "UttarPradesh.svg",
    "wikiLink": "https://en.wikipedia.org/wiki/Uttar_Pradesh",
    "official_website": "https://up.gov.in",
    "isActive": true
  },
  {
    "id": "uttarakhand",
    "state_id": 27,
    "name": "Uttarakhand",
    "dance": "Barada Nati",
    "festival": "Kumaoni Holi",
    "description": "Barada Nati is a folk dance performed in the Jaunsar-Bawar region of Uttarakhand.",
    "image": "uttarakhand.jpeg",
    "svg": "Uttarakhand.svg",
    "wikiLink": "https://en.wikipedia.org/wiki/Uttarakhand",
    "official_website": "https://uk.gov.in",
    "isActive": true
  },
  {
    "id": "westbengal",
    "state_id": 28,
    "name": "West Bengal",
    "dance": "Chhau Dance",
    "festival": "Durga Puja",
    "description": "Chhau Dance is a semi-classical dance form performed in Purulia district of West Bengal.",
    "image": "westbengal.jpg",
    "svg": "WestBengal.svg",
    "wikiLink": "https://en.wikipedia.org/wiki/West_Bengal",
    "official_website": "https://www.wb.gov.in",
    "isActive": true
  },
  {
    "id": "ladakh",
    "state_id": 29,
    "name": "Ladakh",
    "dance": "Shondol Dance",
    "festival": "Losar",
    "description": "The Shondol Dance, performed during the famous Ladakh festival, is known as the 'royal dance of Ladakh'. It is a cultural tradition showcasing the region's rich heritage.",
    "image": "ladakh.jpg",
    "svg": "Ladakh.svg",
    "wikiLink": "https://en.wikipedia.org/wiki/Ladakh",
    "official_website": "https://ladakh.nic.in",
    "isActive": true
  },
  {
    "id": "pondicherry",
    "state_id": 30,
    "name": "Pondicherry",
    "dance": "Bharatanatyam",
    "festival": "Masi Magam",
    "description": "Bharatanatyam in Puducherry reflects the unique blend of Tamil and French cultural influences. The dance form is regularly performed during cultural festivals and celebrations.",
    "image": "puducherry.jpg",
    "svg": "Puducherry.svg",
    "wikiLink": "https://en.wikipedia.org/wiki/Puducherry",
    "official_website": "https://www.py.gov.in",
    "isActive": true
  },
  {
    "id": "andaman-and-nicobar",
    "state_id": 31,
    "name": "Andaman and Nicobar Islands",
    "dance": "Nicobari Dance",
    "festival": "Island Tourism Festival",
    "description": "The Nicobari Dance is a traditional dance form of the indigenous people of the Nicobar Islands. It features unique movements that tell stories of island life and tribal traditions.",
    "image": "andaman.jpg",
    "svg": "Andaman.svg",
    "wikiLink": "https://en.wikipedia.org/wiki/Andaman_and_Nicobar_Islands",
    "official_website": "https://www.andaman.gov.in",
    "isActive": true
  },
  {
    "id": "chandigarh",
    "state_id": 32,
    "name": "Chandigarh",
    "dance": "Bhangra",
    "festival": "Rose Festival",
    "description": "While Chandigarh shares the vibrant Bhangra tradition with Punjab, the city has developed its own unique modern interpretation of this energetic dance form, often showcased during the famous Rose Festival.",
    "image": "chandigarh.jpg",
    "svg": "Chandigarh.svg",
    "wikiLink": "https://en.wikipedia.org/wiki/Chandigarh",
    "official_website": "http://chandigarh.gov.in",
    "isActive": true
  },
  {
    "id": "dadra-and-nagar-haveli-and-daman-and-diu",
    "state_id": 33,
    "name": "Dadra and Nagar Haveli and Daman and Diu",
    "dance": "Tarpa Dance",
    "festival": "Kalo Dungar Festival",
    "description": "The Tarpa Dance, named after the traditional trumpet-like instrument Tarpa, is performed by the Warli and other tribes. Dancers move in circles to the rhythm of the Tarpa instrument.",
    "image": "dadra.jpg",
    "svg": "Dadra.svg",
    "wikiLink": "https://en.wikipedia.org/wiki/Dadra_and_Nagar_Haveli_and_Daman_and_Diu",
    "official_website": "https://dnh.gov.in",
    "isActive": true
  },
  {
    "id": "lakshadweep",
    "state_id": 34,
    "name": "Lakshadweep",
    "dance": "Lava Dance",
    "festival": "Eid-ul-Fitr",
    "description": "The Lava Dance is a traditional Muslim folk dance of Lakshadweep. Performed during celebrations, it reflects the islands' rich maritime culture and Islamic traditions.",
    "image": "lakshadweep.jpg",
    "svg": "Lakshadweep.svg",
    "wikiLink": "https://en.wikipedia.org/wiki/Lakshadweep",
    "official_website": "https://lakshadweep.gov.in",
    "isActive": true
  }
]